os_win/__init__.py
os_win/_i18n.py
os_win/_utils.py
os_win/conf.py
os_win/constants.py
os_win/exceptions.py
os_win/utilsfactory.py
os_win/version.py
os_win/_hacking/__init__.py
os_win/_hacking/checks.py
os_win/tests/__init__.py
os_win/tests/functional/__init__.py
os_win/tests/functional/test_base.py
os_win/tests/functional/test_mutex.py
os_win/tests/functional/test_pathutils.py
os_win/tests/functional/test_vhdutils.py
os_win/tests/unit/__init__.py
os_win/tests/unit/test_base.py
os_win/tests/unit/test_hacking.py
os_win/tests/unit/test_processutils.py
os_win/tests/unit/test_utils.py
os_win/tests/unit/test_utilsfactory.py
os_win/tests/unit/utils/__init__.py
os_win/tests/unit/utils/test_aclutils.py
os_win/tests/unit/utils/test_baseutils.py
os_win/tests/unit/utils/test_hostutils.py
os_win/tests/unit/utils/test_hostutils10.py
os_win/tests/unit/utils/test_jobutils.py
os_win/tests/unit/utils/test_pathutils.py
os_win/tests/unit/utils/test_win32utils.py
os_win/tests/unit/utils/test_wqlutils.py
os_win/tests/unit/utils/compute/__init__.py
os_win/tests/unit/utils/compute/test_clusapi_utils.py
os_win/tests/unit/utils/compute/test_clusterutils.py
os_win/tests/unit/utils/compute/test_livemigrationutils.py
os_win/tests/unit/utils/compute/test_migrationutils.py
os_win/tests/unit/utils/compute/test_rdpconsoleutils.py
os_win/tests/unit/utils/compute/test_vmutils.py
os_win/tests/unit/utils/compute/test_vmutils10.py
os_win/tests/unit/utils/dns/__init__.py
os_win/tests/unit/utils/dns/test_dnsutils.py
os_win/tests/unit/utils/io/__init__.py
os_win/tests/unit/utils/io/test_ioutils.py
os_win/tests/unit/utils/io/test_namedpipe.py
os_win/tests/unit/utils/metrics/__init__.py
os_win/tests/unit/utils/metrics/test_metricsutils.py
os_win/tests/unit/utils/network/__init__.py
os_win/tests/unit/utils/network/test_networkutils.py
os_win/tests/unit/utils/network/test_nvgreutils.py
os_win/tests/unit/utils/storage/__init__.py
os_win/tests/unit/utils/storage/test_diskutils.py
os_win-5.9.0.dist-info/AUTHORS
os_win-5.9.0.dist-info/LICENSE
os_win-5.9.0.dist-info/METADATA
os_win-5.9.0.dist-info/WHEEL
os_win-5.9.0.dist-info/entry_points.txt
os_win-5.9.0.dist-info/pbr.json
os_win-5.9.0.dist-info/top_level.txt
os_win-5.9.0.dist-info/RECORD
